{
  "date": "2026-07-16",
  "pipeline_stage": "stage3_7am",
  "created_at": "2026-07-15T18:22:49.662608+09:00",
  "updated_at": "2026-07-16T06:12:30.601707+09:00",
  "jiai": {
    "screening_jiai": "GREEN",
    "narrative_status": "YELLOW",
    "direction_7am": "NEUTRAL",
    "direction_confidence": "低",
    "morning_jiai": null,
    "effective_jiai": null,
    "futures_direction": null,
    "final_judgment": null
  },
  "market": {
    "nikkei_change": "2.24%",
    "topix_change": null,
    "dow_change": "52,659ドル（+0.29%）",
    "nasdaq_change": "26,269（+0.62%）",
    "futures_gap_pct": -0.7473622508792497,
    "vix": "15.7",
    "usdjpy": "162.15円（-0.28円）",
    "sector_top3": [],
    "sector_worst3": []
  },
  "narrative": {
    "headline": "中東リスクと米金利動向による綱引き相場",
    "risks": [
      {
        "topic": "中東情勢の緊迫化",
        "severity": "high",
        "timeframe": "immediate",
        "sectors": [
          "石油・石炭製品",
          "海運",
          "保険"
        ],
        "detail": "ホルムズ海峡周辺での軍事衝突懸念が原油価格を押し上げ、供給リスクと物流コスト増が日本株の上値を抑制。"
      },
      {
        "topic": "米利上げ観測",
        "severity": "medium",
        "timeframe": "short_term",
        "sectors": [
          "半導体",
          "電気機器",
          "グロース株"
        ],
        "detail": "米FRBのタカ派的な言及が長期金利上昇を招き、ハイテク株や半導体関連株のバリュエーション調整圧力が継続。"
      }
    ],
    "catalysts": [
      {
        "topic": "米CPI鈍化とインフレ沈静化",
        "direction": "positive",
        "timeframe": "short_term",
        "sectors": [
          "全セクター",
          "ハイテク"
        ],
        "detail": "予想を下回るCPI結果により、過度な利上げ懸念が後退。ハイテク株のリバウンドを支える構造的材料。"
      },
      {
        "topic": "半導体大手決算",
        "direction": "positive",
        "timeframe": "short_term",
        "sectors": [
          "半導体",
          "機械"
        ],
        "detail": "ASML等の好決算はAI需要の底堅さを示唆し、日本市場の半導体関連株への見直し買いを誘発する可能性。"
      }
    ]
  },
  "candidates": [
    {
      "code": "6315",
      "name": "ＴＯＷＡ",
      "sector": "機械",
      "type": "順張り",
      "rank": "厳選",
      "close": 3400,
      "day_change": 6.25,
      "turnover": 156.2,
      "avg_range": 7.2,
      "vol_ratio": 1.1,
      "high52w": 3735,
      "backtest_winrate": 65,
      "backtest_expected": 0.55,
      "news_sentiment": "neutral",
      "news_summary": "クラウド・STAGE2で分析",
      "institution_badge": "",
      "sector_score": 4.59,
      "warning_flags": [],
      "warning_label": "",
      "sector_short_ratio": 0.4643,
      "sector_short_status": "中立",
      "sector_short_label": "📊業種空売り中立(46.4%)",
      "entry_base": {
        "low": 3383,
        "high": 3416
      },
      "stop_loss_base": 3335,
      "target_base": 3502,
      "lot_base": 1235,
      "status": "active",
      "added_at": "stage1_screening",
      "flags": [
        "📉減益",
        "📈半導体大手決算"
      ],
      "history": [
        {
          "stage": "stage1_screening",
          "action": "selected",
          "reason": "順張り厳選条件クリア"
        },
        {
          "stage": "stage1.5",
          "action": "flagged",
          "reason": "📉減益"
        },
        {
          "stage": "stage2",
          "action": "flagged",
          "reason": "📈半導体大手決算"
        }
      ],
      "fundamental": {
        "fiscal_year": 2026,
        "roe": 7.0,
        "operating_margin": 12.7,
        "revenue_growth": 1.7,
        "oi_growth": -22.1,
        "equity_ratio": 66.4,
        "dividend_yield": 0.9
      },
      "entry_current": {
        "est_open": 3374,
        "low": 3357,
        "high": 3390
      },
      "stop_loss_current": 3309,
      "target_current": 3475,
      "lot_current": 1244,
      "gap_pct": -0.76
    },
    {
      "code": "6361",
      "name": "荏原製作所",
      "sector": "機械",
      "type": "順張り",
      "rank": "厳選",
      "close": 6230,
      "day_change": 5.93,
      "turnover": 201.9,
      "avg_range": 5.0,
      "vol_ratio": 1.0,
      "high52w": 6890,
      "backtest_winrate": 65,
      "backtest_expected": 0.55,
      "news_sentiment": "neutral",
      "news_summary": "クラウド・STAGE2で分析",
      "institution_badge": "",
      "sector_score": 4.27,
      "warning_flags": [],
      "warning_label": "",
      "sector_short_ratio": 0.4643,
      "sector_short_status": "中立",
      "sector_short_label": "📊業種空売り中立(46.4%)",
      "entry_base": {
        "low": 6198,
        "high": 6261
      },
      "stop_loss_base": 6111,
      "target_base": 6416,
      "lot_base": 674,
      "status": "active",
      "added_at": "stage1_screening",
      "flags": [
        "📊ROE優秀",
        "📈半導体大手決算"
      ],
      "history": [
        {
          "stage": "stage1_screening",
          "action": "selected",
          "reason": "順張り厳選条件クリア"
        },
        {
          "stage": "stage1.5",
          "action": "flagged",
          "reason": "📊ROE優秀"
        },
        {
          "stage": "stage2",
          "action": "flagged",
          "reason": "📈半導体大手決算"
        }
      ],
      "fundamental": {
        "fiscal_year": 2025,
        "roe": 15.6,
        "operating_margin": 11.9,
        "revenue_growth": 10.6,
        "oi_growth": 16.2,
        "equity_ratio": 47.0,
        "dividend_yield": 1.6
      },
      "entry_current": {
        "est_open": 6183,
        "low": 6152,
        "high": 6213
      },
      "stop_loss_current": 6065,
      "target_current": 6368,
      "lot_current": 679,
      "gap_pct": -0.75
    },
    {
      "code": "4062",
      "name": "イビデン",
      "sector": "電気機器",
      "type": "順張り",
      "rank": "厳選",
      "close": 19340,
      "day_change": 7.56,
      "turnover": 1674.4,
      "avg_range": 9.1,
      "vol_ratio": 0.9,
      "high52w": 27480,
      "backtest_winrate": 65,
      "backtest_expected": 0.55,
      "news_sentiment": "neutral",
      "news_summary": "クラウド・STAGE2で分析",
      "institution_badge": "",
      "sector_score": 5.71,
      "warning_flags": [],
      "warning_label": "",
      "sector_short_ratio": 0.3528,
      "sector_short_status": "空売り低位",
      "sector_short_label": "📈業種空売り低位(35.3%)",
      "entry_base": {
        "low": 19243,
        "high": 19436
      },
      "stop_loss_base": 18972,
      "target_base": 19920,
      "lot_base": 217,
      "status": "active",
      "added_at": "stage1_screening",
      "flags": [
        "📊財務良好",
        "📈増益",
        "⚠️米利上げ観測"
      ],
      "history": [
        {
          "stage": "stage1_screening",
          "action": "selected",
          "reason": "順張り厳選条件クリア"
        },
        {
          "stage": "stage1.5",
          "action": "flagged",
          "reason": "📊財務良好"
        },
        {
          "stage": "stage1.5",
          "action": "flagged",
          "reason": "📈増益"
        },
        {
          "stage": "stage2",
          "action": "flagged",
          "reason": "⚠️米利上げ観測"
        }
      ],
      "fundamental": {
        "fiscal_year": 2026,
        "roe": 12.1,
        "operating_margin": 14.9,
        "revenue_growth": 12.7,
        "oi_growth": 30.3,
        "equity_ratio": 58.0,
        "dividend_yield": 0.61
      },
      "entry_current": {
        "est_open": 19195,
        "low": 19099,
        "high": 19290
      },
      "stop_loss_current": 18830,
      "target_current": 19770,
      "lot_current": 218,
      "gap_pct": -0.75
    },
    {
      "code": "6857",
      "name": "アドバンテスト",
      "sector": "電気機器",
      "type": "順張り",
      "rank": "厳選",
      "close": 31510,
      "day_change": 5.83,
      "turnover": 2454.5,
      "avg_range": 5.6,
      "vol_ratio": 0.9,
      "high52w": 35940,
      "backtest_winrate": 65,
      "backtest_expected": 0.55,
      "news_sentiment": "neutral",
      "news_summary": "クラウド・STAGE2で分析",
      "institution_badge": "",
      "sector_score": 3.97,
      "warning_flags": [],
      "warning_label": "",
      "sector_short_ratio": 0.3528,
      "sector_short_status": "空売り低位",
      "sector_short_label": "📈業種空売り低位(35.3%)",
      "entry_base": {
        "low": 31352,
        "high": 31667
      },
      "stop_loss_base": 30911,
      "target_base": 32455,
      "lot_base": 133,
      "status": "active",
      "added_at": "stage1_screening",
      "flags": [
        "📊ROE優秀",
        "📊高収益",
        "📈高成長",
        "📈増益",
        "⚠️米利上げ観測"
      ],
      "history": [
        {
          "stage": "stage1_screening",
          "action": "selected",
          "reason": "順張り厳選条件クリア"
        },
        {
          "stage": "stage1.5",
          "action": "flagged",
          "reason": "📊ROE優秀"
        },
        {
          "stage": "stage1.5",
          "action": "flagged",
          "reason": "📊高収益"
        },
        {
          "stage": "stage1.5",
          "action": "flagged",
          "reason": "📈高成長"
        },
        {
          "stage": "stage1.5",
          "action": "flagged",
          "reason": "📈増益"
        },
        {
          "stage": "stage2",
          "action": "flagged",
          "reason": "⚠️米利上げ観測"
        }
      ],
      "fundamental": {
        "fiscal_year": 2026,
        "roe": 57.6,
        "operating_margin": 44.2,
        "revenue_growth": 44.7,
        "oi_growth": 118.8,
        "equity_ratio": 67.9,
        "dividend_yield": 0.29
      },
      "entry_current": {
        "est_open": 31274,
        "low": 31117,
        "high": 31430
      },
      "stop_loss_current": 30679,
      "target_current": 32212,
      "lot_current": 134,
      "gap_pct": -0.75
    },
    {
      "code": "7201",
      "name": "日産自動車",
      "sector": "輸送用機器",
      "type": "順張り",
      "rank": "厳選",
      "close": 317,
      "day_change": 3.9,
      "turnover": 116.6,
      "avg_range": 3.1,
      "vol_ratio": 1.1,
      "high52w": 417,
      "backtest_winrate": 65,
      "backtest_expected": 0.55,
      "news_sentiment": "neutral",
      "news_summary": "クラウド・STAGE2で分析",
      "institution_badge": "",
      "sector_score": 2.55,
      "warning_flags": [],
      "warning_label": "",
      "sector_short_ratio": 0.5111,
      "sector_short_status": "中立",
      "sector_short_label": "📊業種空売り中立(51.1%)",
      "entry_base": {
        "low": 315,
        "high": 318
      },
      "stop_loss_base": 310,
      "target_base": 326,
      "lot_base": 13249,
      "status": "active",
      "added_at": "stage1_screening",
      "flags": [
        "⚠️ROE低迷",
        "⚠️低収益"
      ],
      "history": [
        {
          "stage": "stage1_screening",
          "action": "selected",
          "reason": "順張り厳選条件クリア"
        },
        {
          "stage": "stage1.5",
          "action": "flagged",
          "reason": "⚠️ROE低迷"
        },
        {
          "stage": "stage1.5",
          "action": "flagged",
          "reason": "⚠️低収益"
        }
      ],
      "fundamental": {
        "fiscal_year": 2026,
        "roe": -10.0,
        "operating_margin": 0.5,
        "revenue_growth": -4.9,
        "oi_growth": -16.9,
        "equity_ratio": 26.5
      },
      "entry_current": {
        "est_open": 314,
        "low": 312,
        "high": 315
      },
      "stop_loss_current": 308,
      "target_current": 323,
      "lot_current": 13375,
      "gap_pct": -0.95
    },
    {
      "code": "3276",
      "name": "ＪＰＭＣ",
      "sector": "不動産業",
      "type": "順張り",
      "rank": "補欠",
      "close": 1721,
      "day_change": 3.93,
      "turnover": 7.0,
      "avg_range": 2.7,
      "vol_ratio": 4.2,
      "high52w": 1827,
      "backtest_winrate": 65,
      "backtest_expected": 0.55,
      "news_sentiment": "neutral",
      "news_summary": "クラウド・STAGE2で分析",
      "institution_badge": "",
      "sector_score": 3.03,
      "warning_flags": [],
      "warning_label": "",
      "sector_short_ratio": 0.3373,
      "sector_short_status": "空売り低位",
      "sector_short_label": "📈業種空売り低位(33.7%)",
      "entry_base": {
        "low": 1712,
        "high": 1729
      },
      "stop_loss_base": 1688,
      "target_base": 1772,
      "lot_base": 2440,
      "status": "active",
      "added_at": "stage1_screening",
      "flags": [
        "📊ROE優秀"
      ],
      "history": [
        {
          "stage": "stage1_screening",
          "action": "selected",
          "reason": "順張り補欠条件クリア"
        },
        {
          "stage": "stage1.5",
          "action": "flagged",
          "reason": "📊ROE優秀"
        }
      ],
      "fundamental": {
        "fiscal_year": 2025,
        "roe": 19.4,
        "operating_margin": 4.5,
        "revenue_growth": -0.8,
        "oi_growth": -3.2,
        "equity_ratio": 53.1,
        "dividend_yield": 4.66
      },
      "entry_current": {
        "est_open": 1708,
        "low": 1699,
        "high": 1716
      },
      "stop_loss_current": 1675,
      "target_current": 1759,
      "lot_current": 2459,
      "gap_pct": -0.76
    },
    {
      "code": "5803",
      "name": "フジクラ",
      "sector": "非鉄金属",
      "type": "順張り",
      "rank": "補欠",
      "close": 5145,
      "day_change": 7.19,
      "turnover": 1686.7,
      "avg_range": 6.4,
      "vol_ratio": 0.7,
      "high52w": 7933,
      "backtest_winrate": 65,
      "backtest_expected": 0.55,
      "news_sentiment": "neutral",
      "news_summary": "クラウド・STAGE2で分析",
      "institution_badge": "",
      "sector_score": 4.85,
      "warning_flags": [],
      "warning_label": "",
      "sector_short_ratio": 0.4902,
      "sector_short_status": "中立",
      "sector_short_label": "📊業種空売り中立(49.0%)",
      "entry_base": {
        "low": 5119,
        "high": 5170
      },
      "stop_loss_base": 5047,
      "target_base": 5299,
      "lot_base": 816,
      "status": "active",
      "added_at": "stage1_screening",
      "flags": [
        "📊ROE優秀",
        "📊高収益",
        "📈高成長",
        "📈増益"
      ],
      "history": [
        {
          "stage": "stage1_screening",
          "action": "selected",
          "reason": "順張り補欠条件クリア"
        },
        {
          "stage": "stage1.5",
          "action": "flagged",
          "reason": "📊ROE優秀"
        },
        {
          "stage": "stage1.5",
          "action": "flagged",
          "reason": "📊高収益"
        },
        {
          "stage": "stage1.5",
          "action": "flagged",
          "reason": "📈高成長"
        },
        {
          "stage": "stage1.5",
          "action": "flagged",
          "reason": "📈増益"
        }
      ],
      "fundamental": {
        "fiscal_year": 2026,
        "roe": 30.6,
        "operating_margin": 16.0,
        "revenue_growth": 20.7,
        "oi_growth": 39.2,
        "equity_ratio": 61.2
      },
      "entry_current": {
        "est_open": 5106,
        "low": 5080,
        "high": 5131
      },
      "stop_loss_current": 5008,
      "target_current": 5259,
      "lot_current": 822,
      "gap_pct": -0.76
    },
    {
      "code": "6525",
      "name": "ＫＯＫＵＳＡＩ　ＥＬＥＣＴＲＩＣ",
      "sector": "電気機器",
      "type": "順張り",
      "rank": "補欠",
      "close": 10850,
      "day_change": 4.78,
      "turnover": 642.7,
      "avg_range": 8.1,
      "vol_ratio": 0.7,
      "high52w": 12220,
      "backtest_winrate": 65,
      "backtest_expected": 0.55,
      "news_sentiment": "neutral",
      "news_summary": "クラウド・STAGE2で分析",
      "institution_badge": "",
      "sector_score": 2.92,
      "warning_flags": [],
      "warning_label": "",
      "sector_short_ratio": 0.3528,
      "sector_short_status": "空売り低位",
      "sector_short_label": "📈業種空売り低位(35.3%)",
      "entry_base": {
        "low": 10795,
        "high": 10904
      },
      "stop_loss_base": 10643,
      "target_base": 11175,
      "lot_base": 387,
      "status": "active",
      "added_at": "stage1_screening",
      "flags": [
        "📊財務良好",
        "📊高収益",
        "⚠️米利上げ観測"
      ],
      "history": [
        {
          "stage": "stage1_screening",
          "action": "selected",
          "reason": "順張り補欠条件クリア"
        },
        {
          "stage": "stage1.5",
          "action": "flagged",
          "reason": "📊財務良好"
        },
        {
          "stage": "stage1.5",
          "action": "flagged",
          "reason": "📊高収益"
        },
        {
          "stage": "stage2",
          "action": "flagged",
          "reason": "⚠️米利上げ観測"
        }
      ],
      "fundamental": {
        "fiscal_year": 2026,
        "roe": 14.5,
        "operating_margin": 17.8,
        "revenue_growth": -1.6,
        "oi_growth": -18.5,
        "equity_ratio": 61.0,
        "dividend_yield": 0.74
      },
      "entry_current": {
        "est_open": 10768,
        "low": 10714,
        "high": 10821
      },
      "stop_loss_current": 10563,
      "target_current": 11091,
      "lot_current": 390,
      "gap_pct": -0.76
    },
    {
      "code": "5016",
      "name": "ＪＸ金属",
      "sector": "非鉄金属",
      "type": "順張り",
      "rank": "補欠",
      "close": 4134,
      "day_change": 6.08,
      "turnover": 802.4,
      "avg_range": 6.6,
      "vol_ratio": 0.6,
      "high52w": 5828,
      "backtest_winrate": 65,
      "backtest_expected": 0.55,
      "news_sentiment": "neutral",
      "news_summary": "クラウド・STAGE2で分析",
      "institution_badge": "",
      "sector_score": 3.74,
      "warning_flags": [],
      "warning_label": "",
      "sector_short_ratio": 0.4902,
      "sector_short_status": "中立",
      "sector_short_label": "📊業種空売り中立(49.0%)",
      "entry_base": {
        "low": 4113,
        "high": 4154
      },
      "stop_loss_base": 4055,
      "target_base": 4258,
      "lot_base": 1015,
      "status": "active",
      "added_at": "stage1_screening",
      "flags": [
        "📊ROE優秀",
        "📊高収益",
        "📈高成長",
        "📈増益"
      ],
      "history": [
        {
          "stage": "stage1_screening",
          "action": "selected",
          "reason": "順張り補欠条件クリア"
        },
        {
          "stage": "stage1.5",
          "action": "flagged",
          "reason": "📊ROE優秀"
        },
        {
          "stage": "stage1.5",
          "action": "flagged",
          "reason": "📊高収益"
        },
        {
          "stage": "stage1.5",
          "action": "flagged",
          "reason": "📈高成長"
        },
        {
          "stage": "stage1.5",
          "action": "flagged",
          "reason": "📈増益"
        }
      ],
      "fundamental": {
        "fiscal_year": 2026,
        "roe": 15.6,
        "operating_margin": 19.8,
        "revenue_growth": 23.7,
        "oi_growth": 55.5,
        "equity_ratio": 48.3,
        "dividend_yield": 0.94
      },
      "entry_current": {
        "est_open": 4103,
        "low": 4082,
        "high": 4123
      },
      "stop_loss_current": 4025,
      "target_current": 4226,
      "lot_current": 1023,
      "gap_pct": -0.75
    },
    {
      "code": "5801",
      "name": "古河電気工業",
      "sector": "非鉄金属",
      "type": "順張り",
      "rank": "補欠",
      "close": 3766,
      "day_change": 6.99,
      "turnover": 624.2,
      "avg_range": 7.5,
      "vol_ratio": 0.6,
      "high52w": 6241,
      "backtest_winrate": 65,
      "backtest_expected": 0.55,
      "news_sentiment": "neutral",
      "news_summary": "クラウド・STAGE2で分析",
      "institution_badge": "",
      "sector_score": 4.65,
      "warning_flags": [],
      "warning_label": "",
      "sector_short_ratio": 0.4902,
      "sector_short_status": "中立",
      "sector_short_label": "📊業種空売り中立(49.0%)",
      "entry_base": {
        "low": 3747,
        "high": 3784
      },
      "stop_loss_base": 3694,
      "target_base": 3878,
      "lot_base": 1115,
      "status": "active",
      "added_at": "stage1_screening",
      "flags": [
        "📊ROE優秀",
        "📈増益"
      ],
      "history": [
        {
          "stage": "stage1_screening",
          "action": "selected",
          "reason": "順張り補欠条件クリア"
        },
        {
          "stage": "stage1.5",
          "action": "flagged",
          "reason": "📊ROE優秀"
        },
        {
          "stage": "stage1.5",
          "action": "flagged",
          "reason": "📈増益"
        }
      ],
      "fundamental": {
        "fiscal_year": 2026,
        "roe": 17.9,
        "operating_margin": 4.9,
        "revenue_growth": 8.8,
        "oi_growth": 35.8,
        "equity_ratio": 40.8,
        "dividend_yield": 0.73
      },
      "entry_current": {
        "est_open": 3737,
        "low": 3718,
        "high": 3755
      },
      "stop_loss_current": 3665,
      "target_current": 3849,
      "lot_current": 1123,
      "gap_pct": -0.77
    },
    {
      "code": "2327",
      "name": "日鉄ソリューションズ",
      "sector": "情報・通信業",
      "type": "SELL",
      "rank": "補欠",
      "close": 3780,
      "day_change": -1.82,
      "turnover": 8.3,
      "avg_range": 2.7,
      "vol_ratio": 0.7,
      "high52w": 3957,
      "backtest_winrate": 68,
      "backtest_expected": 0.63,
      "news_sentiment": "neutral",
      "news_summary": "クラウド・STAGE2で分析",
      "institution_badge": "",
      "sector_score": -61.78,
      "warning_flags": [],
      "warning_label": "",
      "sector_short_ratio": 0.4402,
      "sector_short_status": "中立",
      "sector_short_label": "📊業種空売り中立(44.0%)",
      "entry_base": {
        "low": 3761,
        "high": 3798
      },
      "stop_loss_base": 3708,
      "target_base": 3893,
      "lot_base": 1111,
      "status": "standby",
      "added_at": "stage1_screening",
      "flags": [
        "📊財務良好"
      ],
      "history": [
        {
          "stage": "stage1_screening",
          "action": "selected",
          "reason": "SELL補欠条件クリア"
        },
        {
          "stage": "stage1",
          "action": "active → standby",
          "reason": "GREEN地合い・SELL候補は待機"
        },
        {
          "stage": "stage1.5",
          "action": "flagged",
          "reason": "📊財務良好"
        }
      ],
      "fundamental": {
        "fiscal_year": 2026,
        "roe": 11.4,
        "operating_margin": 11.6,
        "revenue_growth": 12.7,
        "oi_growth": 14.9,
        "equity_ratio": 66.9,
        "dividend_yield": 2.32
      },
      "entry_current": {
        "est_open": 3751,
        "low": 3732,
        "high": 3769
      },
      "stop_loss_current": 3679,
      "target_current": 3863,
      "lot_current": 1119,
      "gap_pct": -0.77
    }
  ],
  "history": [
    {
      "stage": "stage1",
      "action": "3軸スクリーニング完了: 順張り10 SELL1 逆張り0 (active:10 standby:1)",
      "timestamp": "2026-07-15T18:22:49.663759+09:00"
    },
    {
      "stage": "stage1.5",
      "action": "ファンダチェック完了: 11/11銘柄 決算接近警告0 APIリクエスト44",
      "timestamp": "2026-07-15T18:24:06.125101+09:00"
    },
    {
      "stage": "stage2",
      "action": "ナラティブ照合完了: YELLOW リスク2件 触媒2件 (active:10 standby:1)",
      "timestamp": "2026-07-15T21:44:34.073486+09:00"
    },
    {
      "stage": "stage3",
      "action": "7am判定: NEUTRAL（低）先物-0.7% (active:10 standby:1)",
      "timestamp": "2026-07-16T06:12:30.601685+09:00"
    }
  ],
  "stage_metadata": {
    "stage1_screening": {
      "started_at": "2026-07-15T18:22:49.662641+09:00",
      "completed_at": "2026-07-15T18:22:50.574894+09:00"
    },
    "stage1_5_fundamental": {
      "started_at": "2026-07-15T18:22:50.574899+09:00",
      "completed_at": "2026-07-15T21:44:34.073410+09:00"
    },
    "stage2_narrative": {
      "started_at": "2026-07-15T21:44:34.073416+09:00",
      "completed_at": "2026-07-16T06:12:30.601627+09:00"
    },
    "stage3_7am": {
      "started_at": "2026-07-16T06:12:30.601633+09:00"
    }
  }
}